toolslyman/__init__.py
toolslyman/compute_spectrum.py
toolslyman/constants.py
toolslyman/cosmo_calc.py
toolslyman/cosmology.py
toolslyman/cosmology_calc.py
toolslyman/helper_functions.py
toolslyman/igm_tomography.py
toolslyman/ionized_igm.py
toolslyman/lyman_alpha_damping_wings.py
toolslyman/lyman_alpha_transmission.py
toolslyman/mean_profile.py
toolslyman/observational_toolkit.py
toolslyman/plotting_functions.py
toolslyman/scipy_func.py
toolslyman/source_model.py
toolslyman/telescope_filters.py
toolslyman/toy_model.py
toolslyman-0.1.0.dist-info/LICENSE
toolslyman-0.1.0.dist-info/LICENSE.md
toolslyman-0.1.0.dist-info/METADATA
toolslyman-0.1.0.dist-info/WHEEL
toolslyman-0.1.0.dist-info/top_level.txt
toolslyman-0.1.0.dist-info/RECORD
