Metadata-Version: 2.1
Name: toolslyman
Version: 0.1.0
Author: Sambit Giri
Author-email: sambit.giri@gmail.com
License-File: LICENSE
License-File: LICENSE.md
Requires-Dist: numpy
Requires-Dist: scipy
Requires-Dist: matplotlib
Requires-Dist: tqdm
Requires-Dist: astropy
Requires-Dist: tools21cm
Requires-Dist: pytest
